strongline/__init__.py
strongline/services.py
strongline-0.1.1.dist-info/WHEEL
strongline-0.1.1.dist-info/METADATA
strongline-0.1.1.dist-info/RECORD
