Metadata-Version: 2.1
Name: strongline
Version: 0.1.1
Summary: 
Author: Marc Ford
Author-email: mrfxyz567@gmail.com
Requires-Python: >=3.8,<4.0
Classifier: Programming Language :: Python :: 3
Classifier: Programming Language :: Python :: 3.8
Provides-Extra: django
Requires-Dist: channels (>=2.4,<3.0); extra == "django"
Requires-Dist: pydantic (>=1.6.1,<2.0.0)
